mseep_optuna_mcp-1.0.0.dist-info/licenses/LICENSE
optuna_mcp/__init__.py
optuna_mcp/__main__.py
optuna_mcp/py.typed
optuna_mcp/server.py
optuna_mcp/version.py
tests/__init__.py
tests/test_server.py
mseep_optuna_mcp-1.0.0.dist-info/METADATA
mseep_optuna_mcp-1.0.0.dist-info/WHEEL
mseep_optuna_mcp-1.0.0.dist-info/top_level.txt
mseep_optuna_mcp-1.0.0.dist-info/RECORD
