Metadata-Version: 2.4
Name: mseep-optuna-mcp
Version: 1.0.0
Summary: Optuna MCP Server operates, manages, and visualizes Optuna studies.
Home-page: https://github.com/mseep
Author: mseep
Author-email: support@skydeck.ai
Maintainer: mseep
Maintainer-email: support@skydeck.ai
Keywords: mseep
Classifier: Programming Language :: Python :: 3
Classifier: License :: OSI Approved :: MIT License
Classifier: Operating System :: OS Independent
Requires-Python: >=3.6
License-File: LICENSE
Requires-Dist: kaleido==0.2.1
Requires-Dist: mcp[cli]>=1.5.0
Requires-Dist: optuna>=4.2.1
Requires-Dist: optuna-dashboard>=0.18.0
Requires-Dist: pandas>=2.2.3
Requires-Dist: plotly>=6.0.1
Requires-Dist: torch>=2.7.0
Requires-Dist: bottle>=0.13.4
Dynamic: author
Dynamic: author-email
Dynamic: classifier
Dynamic: description
Dynamic: description-content-type
Dynamic: home-page
Dynamic: keywords
Dynamic: license-file
Dynamic: maintainer
Dynamic: maintainer-email
Dynamic: requires-dist
Dynamic: requires-python
Dynamic: summary
